Metadata-Version: 1.0
Name: nli-device
Version: 0.3
Summary: natural language inference for all devices
Home-page: UNKNOWN
Author: UNKNOWN
Author-email: UNKNOWN
License: UNKNOWN
Platform: UNKNOWN
